ctwrap/__init__.py
ctwrap/_version.py
ctwrap/handler.py
ctwrap/output.py
ctwrap/parser.py
ctwrap/strategy.py
ctwrap/wrapper.py
ctwrap/bin/ctwrap.py
ctwrap/modules/__init__.py
ctwrap/modules/equilibrium.py
ctwrap/modules/freeflame.py
ctwrap/modules/ignition.py
ctwrap/modules/minimal.py
ctwrap/modules/solution.py
ctwrap/yaml/equilibrium.yaml
ctwrap/yaml/equilibrium_multi.yaml
ctwrap/yaml/freeflame.yaml
ctwrap/yaml/ignition.yaml
ctwrap/yaml/legacy.yaml
ctwrap/yaml/minimal.yaml
ctwrap/yaml/solution.yaml
ctwrap-0.3.3.dist-info/LICENSE
ctwrap-0.3.3.dist-info/METADATA
ctwrap-0.3.3.dist-info/WHEEL
ctwrap-0.3.3.dist-info/entry_points.txt
ctwrap-0.3.3.dist-info/top_level.txt
ctwrap-0.3.3.dist-info/RECORD
