Metadata-Version: 2.1
Name: ctwrap
Version: 0.3.3
Summary: Python wrapper for batch simulations
Home-page: https://github.com/microcombustion/ctwrap
Author: I. Schoegl and D. Akinpelu
Author-email: ischoegl@lsu.edu
License: MIT
Keywords: python,wrapper,cantera
Platform: UNKNOWN
Classifier: Development Status :: 4 - Beta
Classifier: Intended Audience :: Education
Classifier: Intended Audience :: Science/Research
Classifier: License :: OSI Approved :: MIT License
Classifier: Operating System :: OS Independent
Classifier: Programming Language :: Python :: 3
Requires-Python: >=3.6
Requires-Dist: h5py
Requires-Dist: numpy
Requires-Dist: pandas
Requires-Dist: pint
Requires-Dist: ruamel.yaml
